<annotation>
	<folder>images_new_2</folder>
	<filename>IMG_20220617_094402.jpg</filename>
	<path>C:\Users\Adnan\Desktop\BA - mat\images_new_2\IMG_20220617_094402.jpg</path>
	<source>
		<database>Unknown</database>
	</source>
	<size>
		<width>3968</width>
		<height>2976</height>
		<depth>3</depth>
	</size>
	<segmented>0</segmented>
	<object>
		<name>WerkStueck</name>
		<pose>Unspecified</pose>
		<truncated>0</truncated>
		<difficult>0</difficult>
		<bndbox>
			<xmin>682</xmin>
			<ymin>177</ymin>
			<xmax>992</xmax>
			<ymax>387</ymax>
		</bndbox>
	</object>
	<object>
		<name>WerkStueck</name>
		<pose>Unspecified</pose>
		<truncated>0</truncated>
		<difficult>0</difficult>
		<bndbox>
			<xmin>1695</xmin>
			<ymin>310</ymin>
			<xmax>2033</xmax>
			<ymax>542</ymax>
		</bndbox>
	</object>
	<object>
		<name>WerkStueck</name>
		<pose>Unspecified</pose>
		<truncated>0</truncated>
		<difficult>0</difficult>
		<bndbox>
			<xmin>2930</xmin>
			<ymin>493</ymin>
			<xmax>3353</xmax>
			<ymax>800</ymax>
		</bndbox>
	</object>
	<object>
		<name>WerkStueck</name>
		<pose>Unspecified</pose>
		<truncated>0</truncated>
		<difficult>0</difficult>
		<bndbox>
			<xmin>953</xmin>
			<ymin>729</ymin>
			<xmax>1208</xmax>
			<ymax>884</ymax>
		</bndbox>
	</object>
	<object>
		<name>WerkStueck</name>
		<pose>Unspecified</pose>
		<truncated>0</truncated>
		<difficult>0</difficult>
		<bndbox>
			<xmin>1827</xmin>
			<ymin>842</ymin>
			<xmax>2114</xmax>
			<ymax>1090</ymax>
		</bndbox>
	</object>
	<object>
		<name>WerkStueck</name>
		<pose>Unspecified</pose>
		<truncated>0</truncated>
		<difficult>0</difficult>
		<bndbox>
			<xmin>2869</xmin>
			<ymin>1045</ymin>
			<xmax>3198</xmax>
			<ymax>1316</ymax>
		</bndbox>
	</object>
	<object>
		<name>WerkStueck</name>
		<pose>Unspecified</pose>
		<truncated>0</truncated>
		<difficult>0</difficult>
		<bndbox>
			<xmin>2817</xmin>
			<ymin>1461</ymin>
			<xmax>3075</xmax>
			<ymax>1706</ymax>
		</bndbox>
	</object>
	<object>
		<name>WerkStueck</name>
		<pose>Unspecified</pose>
		<truncated>0</truncated>
		<difficult>0</difficult>
		<bndbox>
			<xmin>1914</xmin>
			<ymin>1284</ymin>
			<xmax>2159</xmax>
			<ymax>1474</ymax>
		</bndbox>
	</object>
	<object>
		<name>WerkStueck</name>
		<pose>Unspecified</pose>
		<truncated>0</truncated>
		<difficult>0</difficult>
		<bndbox>
			<xmin>1153</xmin>
			<ymin>1129</ymin>
			<xmax>1356</xmax>
			<ymax>1277</ymax>
		</bndbox>
	</object>
	<object>
		<name>Behaelter</name>
		<pose>Unspecified</pose>
		<truncated>0</truncated>
		<difficult>0</difficult>
		<bndbox>
			<xmin>1624</xmin>
			<ymin>287</ymin>
			<xmax>2101</xmax>
			<ymax>755</ymax>
		</bndbox>
	</object>
	<object>
		<name>Behaelter</name>
		<pose>Unspecified</pose>
		<truncated>0</truncated>
		<difficult>0</difficult>
		<bndbox>
			<xmin>2875</xmin>
			<ymin>484</ymin>
			<xmax>3379</xmax>
			<ymax>1003</ymax>
		</bndbox>
	</object>
	<object>
		<name>Behaelter</name>
		<pose>Unspecified</pose>
		<truncated>0</truncated>
		<difficult>0</difficult>
		<bndbox>
			<xmin>643</xmin>
			<ymin>171</ymin>
			<xmax>995</xmax>
			<ymax>568</ymax>
		</bndbox>
	</object>
	<object>
		<name>Behaelter</name>
		<pose>Unspecified</pose>
		<truncated>0</truncated>
		<difficult>0</difficult>
		<bndbox>
			<xmin>904</xmin>
			<ymin>729</ymin>
			<xmax>1221</xmax>
			<ymax>1016</ymax>
		</bndbox>
	</object>
	<object>
		<name>Behaelter</name>
		<pose>Unspecified</pose>
		<truncated>0</truncated>
		<difficult>0</difficult>
		<bndbox>
			<xmin>1785</xmin>
			<ymin>806</ymin>
			<xmax>2130</xmax>
			<ymax>1226</ymax>
		</bndbox>
	</object>
	<object>
		<name>Behaelter</name>
		<pose>Unspecified</pose>
		<truncated>0</truncated>
		<difficult>0</difficult>
		<bndbox>
			<xmin>2830</xmin>
			<ymin>1042</ymin>
			<xmax>3204</xmax>
			<ymax>1468</ymax>
		</bndbox>
	</object>
	<object>
		<name>Behaelter</name>
		<pose>Unspecified</pose>
		<truncated>0</truncated>
		<difficult>0</difficult>
		<bndbox>
			<xmin>1108</xmin>
			<ymin>1132</ymin>
			<xmax>1414</xmax>
			<ymax>1381</ymax>
		</bndbox>
	</object>
	<object>
		<name>Behaelter</name>
		<pose>Unspecified</pose>
		<truncated>0</truncated>
		<difficult>0</difficult>
		<bndbox>
			<xmin>1898</xmin>
			<ymin>1252</ymin>
			<xmax>2156</xmax>
			<ymax>1597</ymax>
		</bndbox>
	</object>
	<object>
		<name>Behaelter</name>
		<pose>Unspecified</pose>
		<truncated>0</truncated>
		<difficult>0</difficult>
		<bndbox>
			<xmin>2769</xmin>
			<ymin>1429</ymin>
			<xmax>3082</xmax>
			<ymax>1758</ymax>
		</bndbox>
	</object>
</annotation>
